{
  "batch_id": "nv23_image231924_c01_ramsey_t2star_scout_20260512_0120",
  "requested_by": "nv-researcher",
  "mode": "execute",
  "requested_sample_id": "NV23",
  "selected_templates": [],
  "natural_language_request": "Single FFT-aware Ramsey/T2star scout for image231924_c01 after weak-pi pODMR center.",
  "items": [
    {
      "job_id_prefix": "nv23_image231924_c01_ramsey_t2star_scout",
      "job_id_suffix": "image231924_c01_ramsey_t2star_scout_20260512_0118_execute",
      "mode": "execute",
      "recipe": "xml_generic_v1",
      "sample_id": "NV23",
      "sequence_manifest_id": "auto__ramsey",
      "requested_by": "nv-researcher",
      "submission_path": "single_item_measurement_plan",
      "measurement_plan_verified": true,
      "scan": {
        "vary_prop": [
          "tau"
        ],
        "begin": 0.0,
        "end": 8e-06,
        "points": 51
      },
      "float_vars": {
        "sample_rate": 250000000.0,
        "mw_freq": 3875866666.6666665,
        "det": 2000000.0,
        "mod_depth": 1.0,
        "length_pi_pulse": 5.2e-08,
        "tau": 1e-06,
        "switch_delay": 1e-07,
        "delay_wrt_1mus": 2e-07,
        "wait_time": 2e-06,
        "mw_ampl": -5,
        "ampIQ": 5,
        "freqIQ": 50000000.0,
        "sweep_range": 100000000.0,
        "sweep_time": 1e-06,
        "full_experiment": 0
      },
      "bool_vars": {
        "do_adiabatic_inversion": true
      },
      "acquisition": {
        "average_continuously": false,
        "averages": 4,
        "repetitions": 100000
      },
      "metadata": {
        "project_id": "nv23_aligned_nv_t2star_13c_image231924_20260511_2319",
        "target_label": "image231924_c01",
        "target_role": "ramsey_t2star_13c_fft_scout",
        "weak_pi_review": "<OPENCLAW_WORKSPACE>/.openclaw/projects/nv23_aligned_nv_t2star_13c_image231924_20260511_2319/work/artifacts/analysis/image231924_c01_weak_podmr_20260512_004529_review.json",
        "weak_pi_review_evidence_id": "analysis_20260512_011623_997391_3236a174e0",
        "weak_pi_center_hz": 3875866666.6666665,
        "weak_pi_center_uncertainty_hz": 1000000.0,
        "auto_align_nv": true,
        "require_landmark_match": false,
        "allow_seed_fallback": true,
        "minimum_final_kcps": 12,
        "allow_search_scan": false,
        "search_scan_on_tracking_failure": false,
        "local_fine_search_before_tracking": false,
        "tracking_z_seed_offsets_um": [
          0,
          -0.5,
          0.5,
          1,
          -1
        ],
        "analysis_plan": {
          "kind": "ramsey_t2star_13c_fft_scout",
          "raw_export_and_plot_required": true,
          "fft_analysis_required": true,
          "do_not_auto_fit_in_bridge_job": true,
          "candidate_det_hz": 2000000.0,
          "tau_span_seconds": 8e-06,
          "tau_points": 51,
          "nyquist_hz": 3125000.0,
          "expected_13c_sideband_hz_approx": 390000.0,
          "next_if_usable": "review T2star fit and FFT; decide if repeat/higher quality or CPMG/XY follow-up is needed",
          "next_if_nonclaim_grade": "redesign Ramsey grid/averages based on raw data and advisory before abandoning c01"
        },
        "queue_execute_opt_in": true,
        "requested_by": "nv-researcher",
        "verified_intent_id": "image231924_c01_ramsey_t2star_scout_20260512_0118",
        "execute_route_policy": "validated auto__ramsey manifest; verified intent plus pre-enqueue advisory before managed execute.",
        "frequency_reason": "weak-pi pODMR center 3.875866667 GHz from raw/readout-aware review; center uncertainty ~1 MHz is tolerated by an FFT-aware Ramsey scout.",
        "ramsey_grid_reason": "det=2 MHz over 0..8 us with 51 points gives Nyquist about 3.125 MHz, covering the carrier plus expected ~0.39 MHz 13C sideband without requiring the 101-point grid needed for det=5 MHz.",
        "acquisition_reason": "4 averages x 100000 repetitions gives 400000 shots for the first T2star/FFT scout; even averages preserve snake-order balance and weak-pi drift was not flagged.",
        "comparison_targets": [
          "weak-pi pODMR center 3.875866667 GHz +/- ~1 MHz",
          "Ramsey route review confirmed auto__ramsey has a single tau active path",
          "NV memory Ramsey FFT guardrail: choose det/tau span/points together"
        ],
        "stage": "execute",
        "sequence_manifest_status": "validated",
        "sequence_manifest_scope": "validated",
        "sequence_manifest_path": "<MATLAB_23C_ROOT>\\claw\\sequence_manifests\\validated\\auto__ramsey.json",
        "sequence_path": "<MATLAB_23C_ROOT>\\SavedSequences\\SavedSequences-AWG\\ramsey.xml",
        "sequence_readout_roles": "full_experiment=0 path has readout 1 mS=0 reference before Ramsey and readout 2 post-Ramsey signal.",
        "sequence_bool_vars": {
          "do_adiabatic_inversion": true
        },
        "intent": "image231924 c01 Ramsey/T2star FFT scout after weak-pi center; terminal raw/readout and FFT review required before T2star/13C claims.",
        "nv_position": [
          112.821,
          113.251,
          114.276
        ]
      },
      "intent": "image231924 c01 Ramsey/T2star FFT scout after weak-pi center; terminal raw/readout and FFT review required before T2star/13C claims.",
      "nv_position": [
        112.821,
        113.251,
        114.276
      ],
      "allow_seed_fallback": true,
      "id": "image231924_c01_ramsey_t2star_scout_20260512_0118"
    }
  ],
  "policy": {
    "measurement_plan_enabled": false,
    "measurement_plan_required": false,
    "measurement_plan_advisory_only": true,
    "pre_enqueue_advisory_enabled": true,
    "pre_enqueue_advisory_required": false,
    "max_attempts_per_item": 1,
    "agent_recovery_enabled": false
  }
}